tides/__init__.py
tides/tides.py
tides/bin/__init__.py
tides/bin/classify_orfs.py
tides/bin/filt_seqs.py
tides/bin/orf_call.py
tides/bin/orf_composition.py
tides/bin/orf_prep.py
tides/bin/save_preds.py
TIdeS_ML-1.3.4.dist-info/LICENSE
TIdeS_ML-1.3.4.dist-info/METADATA
TIdeS_ML-1.3.4.dist-info/WHEEL
TIdeS_ML-1.3.4.dist-info/entry_points.txt
TIdeS_ML-1.3.4.dist-info/top_level.txt
TIdeS_ML-1.3.4.dist-info/RECORD
