Metadata-Version: 2.1
Name: TIdeS-ML
Version: 1.3.4
Summary: Tool for ORF-calling and ORF-classification using ML approaches
Home-page: https://github.com/xxmalcala/TIdeS
Author: Xyrus X. Maurer-Alcala
Author-email: xmaurer-alcala@amnh.org
License: MIT
Platform: UNKNOWN
Classifier: Intended Audience :: Science/Research
Classifier: Intended Audience :: Developers
Classifier: Intended Audience :: Science/Research
Classifier: License :: Freely Distributable
Classifier: Development Status :: 5 - Production/Stable
Classifier: Operating System :: OS Independent
Classifier: Programming Language :: Python
Classifier: Programming Language :: Python :: 3
Classifier: Programming Language :: Python :: 3.7
Classifier: Programming Language :: Python :: 3.8
Classifier: Programming Language :: Python :: 3.9
Classifier: Programming Language :: Python :: 3.10
Classifier: Programming Language :: Python :: 3.11
Classifier: Topic :: Scientific/Engineering
Classifier: Topic :: Scientific/Engineering :: Bio-Informatics
Requires-Python: <= 3.11
License-File: LICENSE
Requires-Dist: biopython (==1.79)
Requires-Dist: ete3 (>=3.1.2)
Requires-Dist: optuna (>=3.1.1)
Requires-Dist: pandas (==2.1.1)
Requires-Dist: scikit-learn (>=1.5.0)
Requires-Dist: seaborn (>=0.12.2)
